inkcode.py
InkCode-1.0.dist-info/LICENSE
InkCode-1.0.dist-info/METADATA
InkCode-1.0.dist-info/WHEEL
InkCode-1.0.dist-info/top_level.txt
InkCode-1.0.dist-info/RECORD
