Metadata-Version: 2.1
Name: InkCode
Version: 1.0
Summary: Coloring and formatting text in ANSI-compatible terminals
Author-email: Tomas Illuminati <tomiluminati@gmail.com>
Project-URL: Homepage, https://github.com/tomasilluminati/InkCode
Project-URL: Issues, https://github.com/tomasilluminati/InkCode/issues
Classifier: Programming Language :: Python :: 3
Classifier: License :: OSI Approved :: MIT License
Classifier: Operating System :: OS Independent
Requires-Python: >=3.11
License-File: LICENSE
